pvacseq/__init__.py
pvacseq/pvacseq.py
pvacseq/VEP_plugins/Wildtype.pm
pvacseq/example_data/additional_input_file_list.yaml
pvacseq/example_data/genes.fpkm_tracking
pvacseq/example_data/indels.bam_readcount
pvacseq/example_data/input.vcf
pvacseq/example_data/isoforms.fpkm_tracking
pvacseq/example_data/snvs.bam_readcount
pvacseq/example_data/MHC_Class_I/Test.chop.tsv
pvacseq/example_data/MHC_Class_I/Test.combined.parsed.tsv
pvacseq/example_data/MHC_Class_I/Test.filtered.binding.tsv
pvacseq/example_data/MHC_Class_I/Test.filtered.coverage.tsv
pvacseq/example_data/MHC_Class_I/Test.final.tsv
pvacseq/example_data/MHC_Class_I/Test.stab.tsv
pvacseq/example_data/MHC_Class_I/Test.tsv
pvacseq/example_data/MHC_Class_I/Test.tsv_1-24
pvacseq/example_data/MHC_Class_I/log/inputs.yml
pvacseq/example_data/MHC_Class_I/tmp/Test.HLA-E*01:01.10.parsed.tsv_1-48
pvacseq/example_data/MHC_Class_I/tmp/Test.HLA-E*01:01.9.parsed.tsv_1-48
pvacseq/example_data/MHC_Class_I/tmp/Test.HLA-G*01:09.10.parsed.tsv_1-48
pvacseq/example_data/MHC_Class_I/tmp/Test.HLA-G*01:09.9.parsed.tsv_1-48
pvacseq/example_data/MHC_Class_I/tmp/Test.ann.HLA-E*01:01.10.tsv_1-48
pvacseq/example_data/MHC_Class_I/tmp/Test.ann.HLA-E*01:01.9.tsv_1-48
pvacseq/example_data/MHC_Class_I/tmp/Test.pickpocket.HLA-E*01:01.10.tsv_1-48
pvacseq/example_data/MHC_Class_I/tmp/Test.pickpocket.HLA-E*01:01.9.tsv_1-48
pvacseq/example_data/MHC_Class_I/tmp/Test.pickpocket.HLA-G*01:09.10.tsv_1-48
pvacseq/example_data/MHC_Class_I/tmp/Test.pickpocket.HLA-G*01:09.9.tsv_1-48
pvacseq/example_data/MHC_Class_I/tmp/Test_21.fa.split_1-48
pvacseq/example_data/MHC_Class_I/tmp/Test_21.fa.split_1-48.key
pvacseq/example_data/MHC_Class_II/Test.chop.tsv
pvacseq/example_data/MHC_Class_II/Test.combined.parsed.tsv
pvacseq/example_data/MHC_Class_II/Test.filtered.binding.tsv
pvacseq/example_data/MHC_Class_II/Test.filtered.coverage.tsv
pvacseq/example_data/MHC_Class_II/Test.final.tsv
pvacseq/example_data/MHC_Class_II/Test.tsv
pvacseq-4.0.10.dist-info/DESCRIPTION.rst
pvacseq-4.0.10.dist-info/METADATA
pvacseq-4.0.10.dist-info/RECORD
pvacseq-4.0.10.dist-info/WHEEL
pvacseq-4.0.10.dist-info/entry_points.txt
pvacseq-4.0.10.dist-info/metadata.json
pvacseq-4.0.10.dist-info/top_level.txt
